google_nest_sdm/__init__.py
google_nest_sdm/admin_client.py
google_nest_sdm/auth.py
google_nest_sdm/camera_traits.py
google_nest_sdm/device.py
google_nest_sdm/device_manager.py
google_nest_sdm/device_traits.py
google_nest_sdm/diagnostics.py
google_nest_sdm/doorbell_traits.py
google_nest_sdm/event.py
google_nest_sdm/event_media.py
google_nest_sdm/exceptions.py
google_nest_sdm/google_nest.py
google_nest_sdm/google_nest_api.py
google_nest_sdm/google_nest_subscriber.py
google_nest_sdm/model.py
google_nest_sdm/py.typed
google_nest_sdm/registry.py
google_nest_sdm/streaming_manager.py
google_nest_sdm/structure.py
google_nest_sdm/subscriber_client.py
google_nest_sdm/thermostat_traits.py
google_nest_sdm/traits.py
google_nest_sdm/transcoder.py
google_nest_sdm/webrtc_util.py
google_nest_sdm-9.1.0.dist-info/licenses/LICENSE
google_nest_sdm-9.1.0.dist-info/METADATA
google_nest_sdm-9.1.0.dist-info/WHEEL
google_nest_sdm-9.1.0.dist-info/top_level.txt
google_nest_sdm-9.1.0.dist-info/RECORD
