Metadata-Version: 2.4
Name: google_nest_sdm
Version: 9.1.0
Summary: Library for the Google Nest SDM API
Author-email: Allen Porter <allen.porter@gmail.com>
License-Expression: Apache-2.0
Project-URL: Source, https://github.com/allenporter/google_nest_sdm
Requires-Python: >=3.13
License-File: LICENSE
Requires-Dist: aiohttp>=3.7.3
Requires-Dist: google-auth>=1.22.0
Requires-Dist: google-auth-oauthlib>=0.4.1
Requires-Dist: google-cloud-pubsub>=2.1.0
Requires-Dist: requests-oauthlib>=1.3.0
Requires-Dist: PyYAML>=6.0
Requires-Dist: mashumaro>=3.12
Dynamic: license-file
